emo_platform/__init__.py
emo_platform/api.py
emo_platform/api_async.py
emo_platform/cli.py
emo_platform/exceptions.py
emo_platform/models.py
emo_platform/response.py
emo_platform/tokens/.gitkeep
emo_platform_api_sdk-1.0.3.dist-info/entry_points.txt
emo_platform_api_sdk-1.0.3.dist-info/LICENSE
emo_platform_api_sdk-1.0.3.dist-info/WHEEL
emo_platform_api_sdk-1.0.3.dist-info/METADATA
emo_platform_api_sdk-1.0.3.dist-info/RECORD
