Metadata-Version: 2.1
Name: emo-platform-api-sdk
Version: 1.0.3
Summary: emo platform api python sdk
Home-page: https://yukai.github.io/emo-platform-api-python/
License: MIT
Author: Keita Ito
Author-email: kito@ux-xu.com
Requires-Python: >=3.7,<4.0
Classifier: License :: OSI Approved :: MIT License
Classifier: Programming Language :: Python :: 3
Classifier: Programming Language :: Python :: 3.7
Classifier: Programming Language :: Python :: 3.8
Classifier: Programming Language :: Python :: 3.9
Requires-Dist: aiohttp (>=3.7.4,<4.0.0)
Requires-Dist: fire (>=0.4.0,<0.5.0)
Requires-Dist: pydantic (>=1.9.0,<2.0.0)
Requires-Dist: requests (>=2.26.0,<3.0.0)
Project-URL: Repository, https://github.com/YUKAI/emo-platform-api-python
